README.md
letsencrypt.py
setup.py
0x01_letsencrypt.egg-info/PKG-INFO
0x01_letsencrypt.egg-info/SOURCES.txt
0x01_letsencrypt.egg-info/dependency_links.txt
0x01_letsencrypt.egg-info/requires.txt
0x01_letsencrypt.egg-info/top_level.txt