Metadata-Version: 1.2
Name: 0x01-letsencrypt
Version: 0.1
Summary: Let's Encrypt library for human beings
Home-page: https://github.com/Smart-Hypercube/autocert
Author: Hypercube
Author-email: hypercube@0x01.me
License: MIT
Platform: UNKNOWN
Classifier: Development Status :: 4 - Beta
Classifier: License :: OSI Approved :: MIT License
Classifier: Programming Language :: Python
Classifier: Programming Language :: Python :: 3 :: Only
Classifier: Programming Language :: Python :: 3.6
Classifier: Programming Language :: Python :: 3.7
Classifier: Topic :: Internet :: WWW/HTTP
Classifier: Topic :: Security
Requires-Python: >=3.6
